{
  "artifactKind": "structured-family-executor-architecture-implementation-plan",
  "projectDataVersion": "v0.55.2",
  "branch": "structured-family-editors-unified",
  "startingCommit": "3f29d358e52f4633110a58b477fd3441c6a9a4d0",
  "latestCommitBeforeSprint": "3f29d358e52f4633110a58b477fd3441c6a9a4d0",
  "goal": "Create a planning-only executor architecture implementation plan for future structured-family safe writes without implementing or wiring an executor.",
  "userDecision": "Approve future executor architecture implementation planning.",
  "executorArchitectureImplementationPlanningApproved": true,
  "actualExecutorImplementationApproved": false,
  "executorImplementationApproved": false,
  "executorWiringApproved": false,
  "realWriteScopeApproved": false,
  "guiRealWriteControlsApproved": false,
  "planningOnly": true,
  "excludedByUser": [
    "actual executor implementation",
    "executor wiring",
    "real config writes",
    "GUI real-write controls",
    "real apply button wiring",
    "family safety ranking",
    "safest-family recommendation",
    "families that should stay blocked",
    "limited activation subset selection",
    "broad activation selection",
    "first family selection",
    "first record selection"
  ],
  "futureModulePlan": [
    "future module name only, not created as executable module",
    "future structured_family_safe_write_executor module boundary",
    "future structured_family_safe_write_plan model boundary",
    "future structured_family_safe_write_preflight model boundary",
    "future structured_family_safe_write_backup model boundary",
    "future structured_family_safe_write_rollback model boundary",
    "future structured_family_safe_write_audit model boundary",
    "all future modules require separate implementation approval before creation"
  ],
  "futureTypePlan": [
    "StructuredFamilySafeWritePlan future type",
    "StructuredFamilySafeWritePreflight future type",
    "StructuredFamilySafeWriteTargetPolicy future type",
    "StructuredFamilySafeWriteBackupPlan future type",
    "StructuredFamilySafeWriteRollbackPlan future type",
    "StructuredFamilySafeWriteApprovalState future type",
    "StructuredFamilySafeWriteExecutionReceipt future type",
    "StructuredFamilySafeWriteAuditRecord future type",
    "StructuredFamilySafeWriteEmergencyStop future type"
  ],
  "futureFunctionPlan": [
    "future build_safe_write_plan function",
    "future validate_safe_write_preflight function",
    "future validate_safe_write_target_policy function",
    "future prepare_safe_write_backup_plan function",
    "future prepare_safe_write_rollback_plan function",
    "future verify_manual_approval_state function",
    "future execute_safe_write function",
    "future verify_safe_write_result function",
    "future emit_safe_write_audit_record function",
    "future emergency_stop_reason function"
  ],
  "futureInterfaceBoundaryPlan": [
    "review-only structured-family projections remain separate from execution",
    "in-memory drafts remain separate from future persisted write plans",
    "rendered record candidates remain separate from real config targets",
    "approval state remains separate from execution receipt",
    "backup plan remains separate from backup execution",
    "rollback plan remains separate from rollback execution",
    "executor boundary remains unreachable from current UI",
    "executor boundary remains disconnected from apply_setting_change",
    "executor boundary remains disconnected from write_flow"
  ],
  "futureExecutorInputPlan": [
    "approved safe write plan",
    "approved config target policy",
    "approved backup policy",
    "approved rollback policy",
    "approved manual confirmation state",
    "validated rendered record candidate",
    "validated version compatibility report",
    "validated unsupported/not-proven preservation report"
  ],
  "futureExecutorOutputPlan": [
    "future execution receipt",
    "future post-write reread report",
    "future post-write validation report",
    "future audit record",
    "future rollback availability report",
    "future emergency stop report on failure"
  ],
  "futureValidationObjectPlan": [
    "parser validation object",
    "semantic validation object",
    "target reread object",
    "candidate render/reread object",
    "manual diff review object",
    "Hyprland verify-config or equivalent object",
    "post-write reread object",
    "post-write verification object",
    "rollback availability object"
  ],
  "futureBackupRestoreObjectPlan": [
    "backup location policy object",
    "backup retention policy object",
    "backup integrity hash object",
    "backup reread proof object",
    "restore target validation object",
    "restore reread proof object",
    "post-restore validation object",
    "restore approval object"
  ],
  "futureRollbackRecoveryObjectPlan": [
    "rollback policy object",
    "failed-write recovery object",
    "interrupted-write recovery object",
    "partial-write recovery object",
    "restore-failure recovery object",
    "emergency stop object",
    "user-visible recovery instruction object",
    "rollback approval object"
  ],
  "futureAuditObjectPlan": [
    "operation summary record",
    "source snapshot summary record",
    "candidate rendered record summary",
    "target policy summary",
    "backup policy summary",
    "rollback policy summary",
    "approval summary",
    "validation summary",
    "failure recovery summary",
    "sensitive data redaction rule"
  ],
  "futureTestPlan": [
    "tests for executor remaining unreachable from UI before wiring approval",
    "tests for executor disconnected from apply_setting_change before approval",
    "tests for executor disconnected from write_flow before approval",
    "tests for blocked plan rejection",
    "tests for unsupported/not-proven record rejection",
    "tests for raw fallback preservation",
    "tests for backup approval requirement",
    "tests for rollback approval requirement",
    "tests for first-real-write approval requirement",
    "tests for no Hyprland reload without reload approval",
    "tests for no runtime mutation without runtime approval",
    "tests for no GUI real-write controls before GUI approval"
  ],
  "futureSourceGuardPlan": [
    "guard against Command:: in planning-only section",
    "guard against fs::write in planning-only section",
    "guard against File::create in planning-only section",
    "guard against write_all in planning-only section",
    "guard against serde_json::to_writer in planning-only section",
    "guard against /home/kyo/.config/hypr/hyprland.conf in planning-only section",
    "guard against ~/.config/hypr in planning-only section",
    "guard against gtk button wiring in planning-only section",
    "guard against connect_clicked real-write wiring in planning-only section"
  ],
  "uiReachabilityBoundary": [
    "no user-facing real-write controls in this sprint",
    "no Apply button wiring for structured-family real writes",
    "no GTK control that can trigger real writes",
    "current UI remains review-only for structured-family records",
    "future GUI design requires separate explicit approval"
  ],
  "futureApprovalGates": [
    "approve actual executor implementation scaffold before any executor module is created",
    "approve executor wiring before any executor is reachable",
    "approve GUI real-write controls before any structured-family real-write control is designed",
    "approve real write scope before any config target can be enabled",
    "approve backup execution before any backup is created",
    "approve restore execution before any restore is executed",
    "approve rollback execution before any rollback is executed",
    "approve reload policy before any reload path is enabled",
    "approve runtime mutation policy before any runtime mutation path is enabled",
    "approve first real config write before any real config write starts"
  ],
  "nonApprovalState": {
    "productionActivationApproved": false,
    "executorImplemented": false,
    "executorWired": false,
    "realWritePathEnabled": false,
    "realConfigTargetEnabled": false,
    "backupCreationEnabled": false,
    "restoreExecutionEnabled": false,
    "rollbackExecutionEnabled": false,
    "hyprctlReloadEnabled": false,
    "runtimeMutationEnabled": false,
    "firstRealConfigWriteApproved": false,
    "guiRealWriteControlsEnabled": false,
    "activationSubsetSelected": false
  },
  "productionActivationApproved": false,
  "executorImplemented": false,
  "executorWired": false,
  "realWritePathEnabled": false,
  "realConfigTargetEnabled": false,
  "backupCreationEnabled": false,
  "restoreExecutionEnabled": false,
  "rollbackExecutionEnabled": false,
  "hyprctlReloadEnabled": false,
  "runtimeMutationEnabled": false,
  "firstRealConfigWriteApproved": false,
  "guiRealWriteControlsEnabled": false,
  "familyRankingExcluded": true,
  "activationSubsetSelected": false,
  "productionReadinessDecision": "not production ready",
  "filesChanged": [
    "src/structured_family.rs",
    "tests/structured_family_unified.rs",
    "data/reports/structured-family-executor-architecture-implementation-plan.v0.55.2.json",
    "data/reports/project-area-continuation-scan.v0.55.2.json",
    "data/reports/current-project-handoff.v0.55.2.json",
    "docs/STRUCTURED-FAMILY-EXECUTOR-ARCHITECTURE-IMPLEMENTATION-PLAN.md",
    "docs/PROJECT-AREA-CONTINUATION-SCAN.md",
    "docs/CURRENT-PROJECT-HANDOFF.md",
    "docs/PROJECT-STATUS.md"
  ],
  "testsAdded": [
    "structured_family_executor_architecture_implementation_plan_is_planning_only",
    "structured_family_executor_architecture_implementation_plan_has_no_write_reload_or_ui_wiring",
    "structured_family_executor_architecture_implementation_plan_report_is_planning_only"
  ],
  "validation": {
    "cargoFmt": "passed",
    "cargoFmtCheck": "passed",
    "cargoCheck": "passed",
    "cargoTest": "passed",
    "jqReports": "passed",
    "gitDiffCheck": "passed",
    "cargoBuildRelease": "passed"
  },
  "gtkEvidenceRoot": "not-run-no-visible-ui-change",
  "nextRecommendedWork": "Stop for explicit user decision: approve or reject actual executor implementation scaffold."
}
